{
    "start": {
        "connected": [
            {
                "socket": 5,
                "local_host": "192.168.1.8",
                "local_port": 62171,
                "remote_host": "192.168.1.8",
                "remote_port": 5201
            }
        ],
        "version": "iperf 3.16+",
        "system_info": "CYGWIN_NT-10.0-22631 DESKTOP-60OKSFH 3.5.3-1.x86_64 2024-04-03 17:25 UTC x86_64",
        "timestamp": {
            "time": "Fri, 25 Oct 2024 10:51:28 GMT",
            "timesecs": 1729853488
        },
        "connecting_to": {
            "host": "192.168.1.8",
            "port": 5201
        },
        "cookie": "gkghqifrcuaie62qe3lccnfq6etrqln2zixt",
        "target_bitrate": 1048576,
        "fq_rate": 0,
        "sock_bufsize": 0,
        "sndbuf_actual": 65536,
        "rcvbuf_actual": 65536,
        "test_start": {
            "protocol": "UDP",
            "num_streams": 1,
            "blksize": 65495,
            "omit": 0,
            "duration": 10,
            "bytes": 0,
            "blocks": 0,
            "reverse": 0,
            "tos": 0,
            "target_bitrate": 1048576,
            "bidir": 0,
            "fqrate": 0,
            "interval": 1
        }
    },
    "intervals": [
        {
            "streams": [
                {
                    "socket": 5,
                    "start": 0,
                    "end": 1.008649,
                    "seconds": 1.0086489915847778,
                    "bytes": 130990,
                    "bits_per_second": 1038934.26627386,
                    "packets": 3,
                    "omitted": false,
                    "sender": true
                }
            ],
            "sum": {
                "start": 0,
                "end": 1.008649,
                "seconds": 1.0086489915847778,
                "bytes": 130990,
                "bits_per_second": 1038934.26627386,
                "packets": 3,
                "omitted": false,
                "sender": true
            }
        },
        {
            "streams": [
                {
                    "socket": 5,
                    "start": 1.008649,
                    "end": 2.012766,
                    "seconds": 1.0041170120239258,
                    "bytes": 130990,
                    "bits_per_second": 1043623.3899551047,
                    "packets": 2,
                    "omitted": false,
                    "sender": true
                }
            ],
            "sum": {
                "start": 1.008649,
                "end": 2.012766,
                "seconds": 1.0041170120239258,
                "bytes": 130990,
                "bits_per_second": 1043623.3899551047,
                "packets": 2,
                "omitted": false,
                "sender": true
            }
        },
        {
            "streams": [
                {
                    "socket": 5,
                    "start": 2.012766,
                    "end": 3.012892,
                    "seconds": 1.0001260042190552,
                    "bytes": 130990,
                    "bits_per_second": 1047787.9742945636,
                    "packets": 2,
                    "omitted": false,
                    "sender": true
                }
            ],
            "sum": {
                "start": 2.012766,
                "end": 3.012892,
                "seconds": 1.0001260042190552,
                "bytes": 130990,
                "bits_per_second": 1047787.9742945636,
                "packets": 2,
                "omitted": false,
                "sender": true
            }
        },
        {
            "streams": [
                {
                    "socket": 5,
                    "start": 3.012892,
                    "end": 4.013412,
                    "seconds": 1.0005199909210205,
                    "bytes": 196485,
                    "bits_per_second": 1571063.0614716841,
                    "packets": 2,
                    "omitted": false,
                    "sender": true
                }
            ],
            "sum": {
                "start": 3.012892,
                "end": 4.013412,
                "seconds": 1.0005199909210205,
                "bytes": 196485,
                "bits_per_second": 1571063.0614716841,
                "packets": 2,
                "omitted": false,
                "sender": true
            }
        },
        {
            "streams": [
                {
                    "socket": 5,
                    "start": 4.013412,
                    "end": 5.003316,
                    "seconds": 0.98990398645401,
                    "bytes": 65495,
                    "bits_per_second": 529303.858929699,
                    "packets": 2,
                    "omitted": false,
                    "sender": true
                }
            ],
            "sum": {
                "start": 4.013412,
                "end": 5.003316,
                "seconds": 0.98990398645401,
                "bytes": 65495,
                "bits_per_second": 529303.858929699,
                "packets": 2,
                "omitted": false,
                "sender": true
            }
        },
        {
            "streams": [
                {
                    "socket": 5,
                    "start": 5.003316,
                    "end": 6.007289,
                    "seconds": 1.0039730072021484,
                    "bytes": 130990,
                    "bits_per_second": 1043773.0820276953,
                    "packets": 1,
                    "omitted": false,
                    "sender": true
                }
            ],
            "sum": {
                "start": 5.003316,
                "end": 6.007289,
                "seconds": 1.0039730072021484,
                "bytes": 130990,
                "bits_per_second": 1043773.0820276953,
                "packets": 1,
                "omitted": false,
                "sender": true
            }
        },
        {
            "streams": [
                {
                    "socket": 5,
                    "start": 6.007289,
                    "end": 7.007203,
                    "seconds": 0.999913990497589,
                    "bytes": 130990,
                    "bits_per_second": 1048010.1388305624,
                    "packets": 2,
                    "omitted": false,
                    "sender": true
                }
            ],
            "sum": {
                "start": 6.007289,
                "end": 7.007203,
                "seconds": 0.999913990497589,
                "bytes": 130990,
                "bits_per_second": 1048010.1388305624,
                "packets": 2,
                "omitted": false,
                "sender": true
            }
        },
        {
            "streams": [
                {
                    "socket": 5,
                    "start": 7.007203,
                    "end": 8.008598,
                    "seconds": 1.0013949871063232,
                    "bytes": 130990,
                    "bits_per_second": 1046460.2015116109,
                    "packets": 3,
                    "omitted": false,
                    "sender": true
                }
            ],
            "sum": {
                "start": 7.007203,
                "end": 8.008598,
                "seconds": 1.0013949871063232,
                "bytes": 130990,
                "bits_per_second": 1046460.2015116109,
                "packets": 3,
                "omitted": false,
                "sender": true
            }
        },
        {
            "streams": [
                {
                    "socket": 5,
                    "start": 8.008598,
                    "end": 9.014252,
                    "seconds": 1.005653977394104,
                    "bytes": 196485,
                    "bits_per_second": 1563042.5925158935,
                    "packets": 2,
                    "omitted": false,
                    "sender": true
                }
            ],
            "sum": {
                "start": 8.008598,
                "end": 9.014252,
                "seconds": 1.005653977394104,
                "bytes": 196485,
                "bits_per_second": 1563042.5925158935,
                "packets": 2,
                "omitted": false,
                "sender": true
            }
        },
        {
            "streams": [
                {
                    "socket": 5,
                    "start": 9.014252,
                    "end": 10.011166,
                    "seconds": 0.996914029121399,
                    "bytes": 130990,
                    "bits_per_second": 1051163.861063881,
                    "packets": 2,
                    "omitted": false,
                    "sender": true
                }
            ],
            "sum": {
                "start": 9.014252,
                "end": 10.011166,
                "seconds": 0.996914029121399,
                "bytes": 130990,
                "bits_per_second": 1051163.861063881,
                "packets": 2,
                "omitted": false,
                "sender": true
            }
        }
    ],
    "end": {
        "streams": [
            {
                "udp": {
                    "socket": 5,
                    "start": 0,
                    "end": 10.011166,
                    "seconds": 10.011166,
                    "bytes": 1375395,
                    "bits_per_second": 1099088.757493383,
                    "jitter_ms": 0.0602508987631615,
                    "lost_packets": 0,
                    "packets": 21,
                    "lost_percent": 0,
                    "out_of_order": 0,
                    "sender": true
                }
            }
        ],
        "sum": {
            "start": 0,
            "end": 10.011694,
            "seconds": 10.011694,
            "bytes": 1375395,
            "bits_per_second": 1099088.757493383,
            "jitter_ms": 0.0602508987631615,
            "lost_packets": 0,
            "packets": 21,
            "lost_percent": 0,
            "sender": true
        },
        "sum_sent": {
            "start": 0,
            "end": 10.011166,
            "seconds": 10.011166,
            "bytes": 1375395,
            "bits_per_second": 1099088.757493383,
            "jitter_ms": 0,
            "lost_packets": 0,
            "packets": 21,
            "lost_percent": 0,
            "sender": true
        },
        "sum_received": {
            "start": 0,
            "end": 10.011694,
            "seconds": 10.011694,
            "bytes": 1375395,
            "bits_per_second": 1099030.7933902096,
            "jitter_ms": 0.0602508987631615,
            "lost_packets": 0,
            "packets": 21,
            "lost_percent": 0,
            "sender": false
        },
        "cpu_utilization_percent": {
            "host_total": 7.166773719101398,
            "host_user": 7.166773719101398,
            "host_system": 0,
            "remote_total": 0,
            "remote_user": 0,
            "remote_system": 0
        }
    }
}